.bzrignore
COPYING
ChangeLog
INSTALL.txt
MANIFEST.in
Makefile
README.txt
TODO.txt
setup.cfg
setup.py
utils.wpr
docs/Makefile
docs/fields.html
docs/fields.txt
docs/index.html
docs/index.txt
docs/install.html
docs/install.txt
docs/modules.html
docs/modules.txt
docs/overview.html
docs/overview.txt
docs/templates.html
docs/templates.txt
softwarefabrica/__init__.py
softwarefabrica.django.utils.egg-info/PKG-INFO
softwarefabrica.django.utils.egg-info/SOURCES.txt
softwarefabrica.django.utils.egg-info/dependency_links.txt
softwarefabrica.django.utils.egg-info/entry_points.txt
softwarefabrica.django.utils.egg-info/namespace_packages.txt
softwarefabrica.django.utils.egg-info/not-zip-safe
softwarefabrica.django.utils.egg-info/requires.txt
softwarefabrica.django.utils.egg-info/top_level.txt
softwarefabrica/django/__init__.py
softwarefabrica/django/utils/IPv4MaskedAddressField.py
softwarefabrica/django/utils/SyntheticUploadedFile.py
softwarefabrica/django/utils/UUIDField.py
softwarefabrica/django/utils/__init__.py
softwarefabrica/django/utils/basicauth.py
softwarefabrica/django/utils/bzrcachedrev.py
softwarefabrica/django/utils/display_profile.py
softwarefabrica/django/utils/djangothreads.py
softwarefabrica/django/utils/finddata.py
softwarefabrica/django/utils/managers.py
softwarefabrica/django/utils/models.py
softwarefabrica/django/utils/runners.py
softwarefabrica/django/utils/templates.py
softwarefabrica/django/utils/tracequeries.py
softwarefabrica/django/utils/usearch.py
softwarefabrica/django/utils/version.py
softwarefabrica/django/utils/viewshelpers.py
softwarefabrica/django/utils/locale/it/LC_MESSAGES/django.mo
softwarefabrica/django/utils/locale/it/LC_MESSAGES/django.po
softwarefabrica/django/utils/middleware/__init__.py
softwarefabrica/django/utils/middleware/logger.py
softwarefabrica/django/utils/middleware/profile.py
softwarefabrica/django/utils/middleware/sqldebug.py
softwarefabrica/django/utils/middleware/stats.py
softwarefabrica/django/utils/templates/utils/paginator.html
softwarefabrica/django/utils/templatetags/__init__.py
softwarefabrica/django/utils/templatetags/basename.py
softwarefabrica/django/utils/templatetags/expr.py
softwarefabrica/django/utils/templatetags/forward_query_param.py
softwarefabrica/django/utils/templatetags/in_list.py
softwarefabrica/django/utils/templatetags/macros.py
softwarefabrica/django/utils/templatetags/paginator.py
