Metadata-Version: 1.0
Name: softwarefabrica.django.utils
Version: 1.0dev-BZR-r115-panta-elasticworld.org-20100520155735-sf3yrsr0pvyvlm8m
Summary: Utility module for SoftwareFabrica django projects
Home-page: http://pypi.python.org/pypi/softwarefabrica.django.utils/
Author: Marco Pantaleoni
Author-email: m.pantaleoni@softwarefabrica.org
License: GNU GPL v2
Download-URL: http://pypi.python.org/packages/source/s/softwarefabrica.django.utils/softwarefabrica.django.utils-1.0dev-BZR-r115-panta-elasticworld.org-20100520155735-sf3yrsr0pvyvlm8m.tar.gz
Keywords: utility utilities django foundation softwarefabrica
Platform: UNKNOWN
Classifier: Development Status :: 4 - Beta
Classifier: Framework :: Django
Classifier: Intended Audience :: Developers
Classifier: License :: OSI Approved :: GNU General Public License (GPL)
Classifier: Operating System :: OS Independent
Classifier: Programming Language :: Python :: 2.3
Classifier: Topic :: Software Development :: Libraries :: Python Modules
